MANIFEST.in
README.md
setup.cfg
setup.py
django_yamaps.egg-info/PKG-INFO
django_yamaps.egg-info/SOURCES.txt
django_yamaps.egg-info/dependency_links.txt
django_yamaps.egg-info/not-zip-safe
django_yamaps.egg-info/requires.txt
django_yamaps.egg-info/top_level.txt
yamaps/__init__.py
yamaps/apps.py
yamaps/forms.py
yamaps/settings.py
yamaps/static/yamaps/js/yamaps-widget.js
yamaps/templatetags/__init__.py
yamaps/templatetags/yamaps.py