Metadata-Version: 1.1
Name: django-yamaps
Version: 0.4.0
Summary: A django widget which allows you to select the address using the yandex map.
Home-page: https://github.com/herald-it/django-yamaps
Author: Dmitry Shlagov
Author-email: wessmoke@gmail.com
License: MIT
Download-URL: https://github.com/herald-it/django-yamaps/archive/0.4.0.tar.gz
Keywords: django,address,yandex,maps,admin
Platform: UNKNOWN
Classifier: Development Status :: 3 - Alpha
Classifier: Framework :: Django
Classifier: Framework :: Django :: 1.9
Classifier: Framework :: Django :: 1.10
Classifier: Framework :: Django :: 1.11
Classifier: Intended Audience :: Developers
Classifier: License :: OSI Approved :: MIT License
Classifier: Natural Language :: Russian
Classifier: Operating System :: OS Independent
Classifier: Programming Language :: Python
Classifier: Programming Language :: Python :: 3
Classifier: Programming Language :: Python :: 3.3
Classifier: Programming Language :: Python :: 3.4
Classifier: Programming Language :: Python :: 3.5
